{
  "cli": {
    "version": ">= 3.0.0",
    "appVersionSource": "remote"
  },
  "build": {
    "development": {
      "developmentClient": true,
      "distribution": "internal",
      "android": {
        "buildType": "apk"
      },
      "node": "20.18.0",
      "env": {
        "EXPO_PUBLIC_API_URL": "https://176.12.72.246.nip.io",
        "GRADLE_OPTS": "-Dorg.gradle.daemon=false -Dorg.gradle.console=plain"
      }
    },
    "preview": {
      "distribution": "internal",
      "android": {
        "buildType": "apk"
      },
      "node": "20.18.0",
      "env": {
        "EXPO_PUBLIC_API_URL": "https://176.12.72.246.nip.io",
        "SENTRY_DISABLE_AUTO_UPLOAD": "true"
      }
    },
    "production": {
      "distribution": "internal",
      "android": {
        "buildType": "apk"
      },
      "node": "20.18.0",
      "env": {
        "EXPO_PUBLIC_API_URL": "https://176.12.72.246.nip.io",
        "EXPO_PUBLIC_N8N_WEBHOOK_URL": "https://timki.app.n8n.cloud/webhook/BunkerV2.4",
        "EXPO_PUBLIC_N8N_CHAT_WEBHOOK_URL": "https://timki.app.n8n.cloud/webhook/BunkerV2.4",
        "SENTRY_DISABLE_AUTO_UPLOAD": "true"
      }
    }
  },
  "submit": {
    "production": {}
  }
}
